odoo/addons/delivery_purchase/README.rst
odoo/addons/delivery_purchase/__init__.py
odoo/addons/delivery_purchase/__manifest__.py
odoo/addons/delivery_purchase/i18n/delivery_purchase.pot
odoo/addons/delivery_purchase/i18n/es.po
odoo/addons/delivery_purchase/models/__init__.py
odoo/addons/delivery_purchase/models/delivery_carrier.py
odoo/addons/delivery_purchase/models/purchase_order.py
odoo/addons/delivery_purchase/models/stock_picking.py
odoo/addons/delivery_purchase/readme/CONTRIBUTORS.rst
odoo/addons/delivery_purchase/readme/DESCRIPTION.rst
odoo/addons/delivery_purchase/readme/USAGE.rst
odoo/addons/delivery_purchase/static/description/icon.png
odoo/addons/delivery_purchase/static/description/index.html
odoo/addons/delivery_purchase/tests/__init__.py
odoo/addons/delivery_purchase/tests/test_delivery_purchase.py
odoo/addons/delivery_purchase/views/purchase_order_view.xml
odoo/addons/delivery_purchase/views/stock_picking_view.xml
odoo14_addon_delivery_purchase-14.0.1.3.0.dist-info/METADATA
odoo14_addon_delivery_purchase-14.0.1.3.0.dist-info/WHEEL
odoo14_addon_delivery_purchase-14.0.1.3.0.dist-info/top_level.txt
odoo14_addon_delivery_purchase-14.0.1.3.0.dist-info/RECORD
